xai_feature_selection/__init__.py
xai_feature_selection/feature_selection.py
xai_feature_selection/model_prediction.py
xai_feature_selection-0.6.dist-info/LICENSE.txt
xai_feature_selection-0.6.dist-info/METADATA
xai_feature_selection-0.6.dist-info/WHEEL
xai_feature_selection-0.6.dist-info/top_level.txt
xai_feature_selection-0.6.dist-info/RECORD
