Metadata-Version: 2.1
Name: xai-feature-selection
Version: 0.6
Summary: Feature selection using XAI
Author: Yaganteeswarudu Akkem
Author-email: yaganteeswaritexpert@gmail.com
Keywords: machine learning,feature selection,explainable artificial intelligence,XAI
Classifier: Development Status :: 1 - Planning
Classifier: Intended Audience :: Developers
Classifier: Programming Language :: Python :: 3
Classifier: Operating System :: Unix
Classifier: Operating System :: MacOS :: MacOS X
Classifier: Operating System :: Microsoft :: Windows
License-File: LICENSE.txt
Requires-Dist: pandas (==2.0.*)
Requires-Dist: lime
Requires-Dist: shap
